odoo/addons/sale_product_set_packaging_qty/README.rst
odoo/addons/sale_product_set_packaging_qty/__init__.py
odoo/addons/sale_product_set_packaging_qty/__manifest__.py
odoo/addons/sale_product_set_packaging_qty/i18n/es.po
odoo/addons/sale_product_set_packaging_qty/i18n/sale_product_set_packaging_qty.pot
odoo/addons/sale_product_set_packaging_qty/models/__init__.py
odoo/addons/sale_product_set_packaging_qty/models/product_set.py
odoo/addons/sale_product_set_packaging_qty/readme/CONTRIBUTORS.rst
odoo/addons/sale_product_set_packaging_qty/readme/CREDITS.rst
odoo/addons/sale_product_set_packaging_qty/readme/DESCRIPTION.rst
odoo/addons/sale_product_set_packaging_qty/static/description/icon.png
odoo/addons/sale_product_set_packaging_qty/static/description/index.html
odoo/addons/sale_product_set_packaging_qty/tests/__init__.py
odoo/addons/sale_product_set_packaging_qty/tests/test_product_set_packaging.py
odoo/addons/sale_product_set_packaging_qty/views/product_set.xml
odoo/addons/sale_product_set_packaging_qty/views/product_set_line.xml
odoo14_addon_sale_product_set_packaging_qty-14.0.1.1.0.dist-info/METADATA
odoo14_addon_sale_product_set_packaging_qty-14.0.1.1.0.dist-info/WHEEL
odoo14_addon_sale_product_set_packaging_qty-14.0.1.1.0.dist-info/top_level.txt
odoo14_addon_sale_product_set_packaging_qty-14.0.1.1.0.dist-info/RECORD
